inputstreamhelper.py
xbmc.py
xbmcaddon.py
xbmcgui.py
xbmcplugin.py
xbmcvfs.py
sakee/__init__.py
sakee/addoninfo.py
sakee/colors.py
sakee/internalplayer.py
sakee/pluginhandler.py
sakee/sakebuiltin.py
sakee/sakejsonrpc.py
sakee/stub.py
sakee-0.1.8.dist-info/LICENSE.md
sakee-0.1.8.dist-info/METADATA
sakee-0.1.8.dist-info/WHEEL
sakee-0.1.8.dist-info/top_level.txt
sakee-0.1.8.dist-info/RECORD
