Metadata-Version: 2.1
Name: sakee
Version: 0.1.8
Summary: SAKÉ can help you to debug and develop Kodi Python add-ons
Home-page: https://github.com/retrospect-addon/kodi.emulator.ascii
Author: Bas Rieter
License: GPL-3.0
Project-URL: Documentation, https://github.com/retrospect-addon/kodi.emulator.ascii/blob/master/README.md
Project-URL: Source, https://github.com/retrospect-addon/kodi.emulator.ascii/
Project-URL: Tracker, https://github.com/retrospect-addon/kodi.emulator.ascii/issues
Keywords: Kodi,emulator,ascii,xbmc,xbmcgui,xbmcplugin,xbmcaddon
Requires-Python: >=3.0
License-File: LICENSE.md
